easygems/healpix/__init__.py
easygems/remap.py
easygems/resample.py
easygems/show.py
easygems/transform.py
easygems-0.1.3.dist-info/METADATA
easygems-0.1.3.dist-info/WHEEL
easygems-0.1.3.dist-info/licenses/LICENSE
easygems-0.1.3.dist-info/RECORD
